{
 "mdsDat": {
 "x": [ -0.1141598, -0.2132921, -0.004354021, 0.0408821, 0.04137437, -0.001265683, 0.08263467, 0.08771683, 0.08202306, 0.06232173, 0.07866501, -0.06057084, -0.03759755, -0.04437778 ],
"y": [ -0.1187893, 0.03861059, 0.03826287, 0.1955559, 0.02408117, -0.04864825, -0.04872528, -0.04608565, -0.03298514, 0.09879004, -0.1103688, 0.01968292, -0.02005298, 0.01067178 ],
"topics": [ 1, 2, 3, 4, 5, 6, 7, 8, 9, 10, 11, 12, 13, 14 ],
"Freq": [ 8.007526, 7.943146, 7.287467, 7.287178,  7.19202, 7.162629, 7.044972,  7.03141, 6.988409, 6.972573, 6.919223, 6.771997, 6.727372, 6.664079 ],
"cluster": [        1,        1,        1,        1,        1,        1,        1,        1,        1,        1,        1,        1,        1,        1 ] 
},
"tinfo": {
 "Term": [ "mathematics", "models", "algorithms", "statistics", "programming", "analysis", "applications", "database", "linear", "random", "software", "probability", "systems", "inference", "designs", "learning", "estimation", "regression", "theory", "management", "computer", "distributions", "series", "equations", "calculus", "information", "trees", "computing", "application", "matrix", "models", "clustering", "machines", "learning", "estimation", "regression", "bounds", "support", "supervised", "reduction", "prediction", "transforming", "discriminant", "neural", "machine_learning", "dimension", "construction", "monte", "kernel", "analyses", "cycle", "networks", "forecasting", "variety", "unsupervised", "response", "analytics", "classification", "ordinary", "code", "random", "probability", "conditional", "distributions", "expectation", "tests", "central", "estimators", "density", "theorem", "limit", "numbers", "law", "gaussian", "regression_models", "likelihood", "maximum", "generating", "moment", "ratio", "distribution", "theory", "estimator", "constraints", "statistics", "independence", "following", "generalized", "convergence", "method", "recurrence", "relevant", "web", "discussion", "knowledge", "information", "engines", "text", "completion", "measurement", "relevance", "testing", "term", "problem", "study", "management", "process", "communication", "collaborative", "nonhomogeneous", "exploration", "theories", "rather", "skill", "definite", "given", "indexing", "ranking", "particular", "subset", "mathematics", "calculus", "derivatives", "integral", "disciplines", "series", "continuity", "sequences", "propositional", "mean", "taylor", "integration", "limits", "proof", "iterative", "integrals", "precise", "briefly", "detail", "transcendental", "curve", "choice", "contradiction", "correctness", "shell", "chain", "majors", "surface", "writing", "induction", "database", "relational", "engineering", "sql", "database_systems", "fundamentals", "fields", "approximation", "query", "structure", "understand", "querying", "technology", "demonstrate", "focusing", "main", "studying", "end", "significant", "discusses", "training", "tutorial", "integrity", "human", "admitted", "systems", "error", "project", "least", "collaboration", "linear", "matrix", "eigenvalues", "equations", "determinants", "transformations", "written", "subspaces", "life", "space", "bases", "planes", "files", "symbolic", "operations", "matrices", "descriptive", "context", "asymptotic", "developing", "transaction", "elimination", "lines", "specializing", "orthogonality", "wave", "entrepreneurship", "symmetric", "electricity", "eigenvectors", "research", "critical", "objectoriented", "marketing", "oral", "emphasizing", "approaches", "introduce", "preparation", "functional", "poisson", "background", "big_data", "specific", "available", "hypothesis_testing", "samples", "explanatory", "splines", "workflows", "multivariable", "best", "extended", "engine", "computational", "algebraic", "different", "patterns", "combinations", "reliability", "skills", "manipulation", "approach", "develop", "change", "inner", "overview", "complexity", "control", "build", "scale", "average", "ridge", "dot", "transformation", "primary", "biology", "indepth", "table", "evidence", "opportunity", "perspective", "lagrange", "business", "surveys", "data_science", "decision", "partial", "data_analysis", "focus", "point", "requirements", "offerings", "applied", "formal", "system", "operating", "evaluation", "linear_regression", "aims", "titles", "test", "cleaning", "exploratory", "dictionaries", "ensemble", "documents", "blocking", "bivariate", "marginal", "placed", "forms", "qualitative", "teamwork", "simplex", "transform", "reading", "environment", "logic", "planning", "algebra", "realworld", "carlo", "multipliers", "education", "several", "confidence", "expressions", "presented", "inheritance", "generation", "discrete", "programming", "computing", "software", "gradient", "multinomial", "variants", "area", "strategic", "documentation", "substituted", "cardinal", "simulationbased", "fulltime", "data_visualization", "analyze", "abstract", "computers", "final", "algorithms", "sets", "satisfy", "binary", "lists", "strategies", "additive", "notions", "teaches", "transforms", "hypotheses", "state", "already", "rank", "policy", "working", "investigate", "rates", "datasets", "heaps", "trees", "hash", "problemsolving", "graph", "sorting", "data_structures", "data_sets", "based", "efficiency", "bias", "inference", "designs", "document", "experimental", "useful", "block", "engl", "experiments", "parameters", "factorial", "estimating", "feedback", "questions", "economics", "exposure", "advances", "excel", "collections", "sampling", "natural", "fourier", "articles", "algorithm", "designed", "relationship", "debugging", "acquisition", "enable", "notation", "complete", "designing", "presentation", "differential_equations", "combinatorial", "interpolation", "public", "behind", "randomization", "computer", "python", "packages", "improvement", "nonlinear_regression", "focused", "contexts", "concurrency", "discovering", "direct", "optics", "selection", "geometric", "provide", "illustrated", "additional", "problems", "balanced", "memory", "financial", "needed", "professional", "computer_science", "function", "complex", "network", "regularization", "multiple", "across", "set", "applications", "records", "assumptions", "widely", "consistency", "uncertainty", "taylors", "ideas", "prerequisites", "community", "scheduling", "goodness", "subsystem", "maple", "biological", "magnetism", "greater", "team", "times", "challenging", "approximations", "commercially", "application", "solution", "technical", "variance", "proofs", "analysis", "graphs", "counting", "variable", "vector", "variable", "simple", "passfail", "spaces", "quantitative", "make", "expected", "basis", "chains", "foundations", "queues", "assessment", "field", "processing", "statistics", "continuous", "continuous", "numerical", "analysis", "regular", "squares", "computation", "differential", "software", "graphical", "optimization", "proofs", "systems", "numerical", "applications", "queues", "theoretical", "data_mining", "visualization", "programming", "automata", "application", "diagonalization", "handson", "interdisciplinary", "power", "grade", "means", "privacy", "analyzing", "markov", "modelling", "structures", "learn", "greedy", "planning", "business", "optimization", "processing", "analysis", "management", "mining", "making", "solving", "predictive", "dynamic", "making", "data_science", "project", "neural_networks", "graph_theory", "specialist", "various", "differential", "practical", "partial", "apply", "apply", "regular", "statistics", "theorems", "computing", "data_mining", "analysis", "visualization", "theoretical", "theory", "simulation", "counting", "sample", "trees", "modelling", "learn", "implementation", "rigorous", "integrals", "simple", "classification", "applications", "estimation", "sample", "time", "data_structures", "writing", "variance", "systems", "optimization", "sampling", "information", "problems", "vector", "series", "application", "computer", "computer", "regression", "probabilistic", "observational", "time", "properties", "time", "programming", "communication", "graphs", "searching", "scripting", "field", "associated", "structures", "memory", "practical", "solution", "representation", "learning", "solving", "structures", "field", "implementation", "project", "algorithmic", "algorithmic", "parallel", "unsupervised", "certain", "parametric", "computation", "strong", "observational", "specification", "regression", "recursive", "theory", "upper", "multivariate", "hypothesis_testing" ],
"logprob": [       30,       29,       28,       27,       26,       25,       24,       23,       22,       21,       20,       19,       18,       17,       16,       15,       14,       13,       12,       11,       10,        9,        8,        7,        6,        5,        4,        3,        2,        1,   -2.143,  -3.9155,  -4.6799,  -3.3059,  -3.3483,  -3.3483,  -5.0772,  -5.0772,  -4.2799,  -4.6799,  -4.3963,  -5.3567,  -5.3567,  -5.3567,   -4.528,  -5.0772,  -5.0772,  -5.0772,  -5.7462,  -5.7462,  -5.7462,  -5.3567,  -5.3567,  -5.0772,  -5.0772,  -5.0772,  -4.6799,  -4.6799,  -5.3567,  -5.7462,  -3.0341,  -3.1355,  -4.0643,  -3.5216,   -4.263,   -4.263,   -4.663,   -4.663,   -4.842,  -3.7566,  -4.3794,  -4.3794,  -5.0603,  -5.0603,  -5.0603,  -3.9781,   -4.663,   -4.663,  -5.3399,  -5.3399,   -4.663,  -3.3314,  -5.7293,  -5.7293,  -2.5181,  -5.3399,  -5.0603,  -5.0603,  -5.3399,  -5.0603,  -4.6404,  -4.6404,  -4.6404,  -4.8587,  -4.3096,  -3.6971,  -4.4614,  -4.1778,  -5.1383,  -5.1383,  -5.1383,  -4.6404,  -4.6404,  -4.3096,  -4.3096,  -3.4908,  -4.4614,  -4.0614,  -5.5277,  -5.5277,  -5.5277,  -5.5277,  -5.5277,  -5.5277,  -5.5277,  -5.5277,  -5.5277,  -5.5277,  -5.5277,  -5.5277,  -1.8403,  -3.5666,  -4.5974,  -4.5974,  -4.5974,  -3.5098,  -4.7765,  -4.7765,  -5.2743,  -5.2743,  -5.2743,  -4.0932,  -4.5974,  -4.3139,  -4.9947,  -4.4456,  -5.6638,  -5.6638,  -5.6638,  -5.6638,  -5.6638,  -5.6638,  -5.6638,  -5.2743,  -5.2743,  -5.2743,  -5.2743,  -5.2743,  -4.3139,  -4.9947,  -2.7667,  -3.8317,  -4.3648,  -4.3648,  -4.5166,  -4.6957,  -4.6957,  -4.9139,  -4.5166,  -5.1935,  -5.1935,  -4.9139,  -4.9139,   -5.583,   -5.583,   -5.583,   -5.583,   -5.583,   -5.583,   -5.583,   -5.583,   -5.583,  -5.1935,  -5.1935,  -5.1935,  -3.1851,  -4.6957,   -3.918,  -4.6957,   -5.583,   -2.801,  -3.7576,  -4.3702,  -3.5514,   -4.701,   -4.701,  -4.9193,  -4.9193,  -4.9193,  -4.3702,  -5.1989,  -5.1989,  -5.1989,  -5.1989,   -4.701,  -4.2384,  -4.9193,  -5.5883,  -5.5883,  -5.5883,  -5.5883,  -5.5883,  -5.5883,  -5.5883,  -5.5883,  -5.5883,  -5.5883,  -5.5883,  -5.5883,   -4.701,  -4.0894,  -4.2058,  -4.0894,  -4.0894,  -4.6684,  -4.6684,  -4.4894,  -5.1663,  -5.1663,  -5.1663,  -4.6684,  -4.4894,  -4.8867,  -4.8867,  -4.8867,  -4.3376,  -5.5557,  -5.5557,  -5.5557,  -5.5557,  -5.5557,  -5.5557,  -5.5557,  -5.5557,  -4.2058,  -5.1663,  -5.1663,  -5.1663,  -5.5557,  -5.5557,  -3.8008,  -4.6647,   -4.883,   -4.883,  -5.1626,  -5.1626,  -4.6647,   -4.883,  -4.3339,   -5.552,   -5.552,   -5.552,   -5.552,   -5.552,   -5.552,   -5.552,   -5.552,   -5.552,   -5.552,   -5.552,   -5.552,   -5.552,  -5.1626,  -3.9814,  -5.1626,  -3.8008,  -4.6647,   -4.883,  -4.4857,   -4.883,  -4.4576,  -4.4576,  -4.4576,  -4.6366,  -4.6366,  -3.7727,  -4.8549,  -4.3058,  -4.4576,  -5.1345,  -5.1345,  -4.8549,  -4.8549,  -4.8549,  -5.5239,  -5.5239,  -5.5239,  -5.5239,  -5.5239,  -5.5239,  -5.5239,  -5.5239,  -5.5239,  -5.5239,  -5.5239,  -5.5239,  -5.1345,  -4.8549,  -4.3058,  -4.8549,  -3.8907,  -4.0894,  -4.6684,  -4.8867,  -4.8867,  -4.3376,  -4.4894,  -5.1663,  -5.1663,  -5.1663,  -5.1663,  -3.9851,  -2.5576,  -3.8045,  -3.1154,  -5.5557,  -5.5557,  -5.5557,  -5.5557,  -5.5557,  -5.5557,  -5.5557,  -5.5557,  -5.5557,  -5.1663,  -4.8867,  -5.5557,  -5.1663,  -5.5557,  -5.1663,  -2.2699,  -3.7859,  -4.6498,  -4.8681,  -4.4708,  -4.4708,  -5.5371,  -5.5371,  -5.5371,  -5.5371,  -5.5371,  -5.5371,  -5.5371,  -5.5371,  -5.5371,  -5.5371,  -5.5371,  -5.5371,  -5.5371,  -5.5371,  -3.7065,  -5.1477,  -5.1477,   -4.319,  -4.6498,   -4.319,  -4.8681,  -5.1477,  -5.5371,  -5.5371,  -3.1639,  -3.2125,  -4.4049,  -3.9007,  -5.0818,  -5.0818,  -5.0818,  -4.4049,  -4.8022,  -4.8022,  -5.4713,  -5.4713,  -5.4713,  -5.4713,  -5.4713,  -5.4713,  -5.4713,  -5.4713,  -3.9007,  -5.0818,  -5.0818,  -5.0818,   -4.584,  -5.0818,  -5.4713,  -5.0818,  -5.4713,  -5.4713,  -5.4713,  -5.4713,  -4.5719,   -4.241,  -4.3928,  -5.0697,  -5.0697,  -5.0697,  -5.0697,  -4.5719,  -3.4223,  -4.7901,  -5.4592,  -5.4592,  -5.4592,  -5.4592,  -5.4592,  -5.4592,  -5.4592,  -5.4592,  -5.4592,  -4.5719,  -5.0697,  -5.0697,  -5.0697,  -4.7901,  -3.8886,  -5.4592,  -5.0697,  -5.4592,  -5.4592,  -5.0697,  -4.1273,  -4.2591,  -4.4109,  -4.0109,  -4.8082,  -3.9067,  -5.0878,  -5.0878,  -2.7197,  -5.4773,  -5.4773,  -5.4773,  -5.4773,  -5.4773,  -5.4773,  -5.4773,  -5.4773,  -5.4773,  -5.4773,  -5.4773,  -5.4773,  -5.4773,  -5.4773,  -5.4773,  -5.0878,  -4.8082,  -5.4773,  -5.4773,  -5.4773,  -6.1239,   -3.918,  -5.1663,  -4.6404,  -4.0614,  -4.3376,  -2.7944,   -4.319,  -4.8082,  -4.8589,  -4.0177,   -4.842,    -4.59,  -5.1383,  -5.1989,  -4.8681,  -5.1383,  -5.1383,  -5.1989,  -4.9193,  -5.1989,  -4.6498,  -5.0697,  -4.8082,  -4.3648,  -3.2125,  -4.8082,  -4.8867,  -4.4708,   -3.348,  -4.8549,  -5.0697,  -4.6366,  -4.9193,  -3.7727,  -5.0697,  -4.6799,  -4.5974,  -3.8886,  -4.5719,  -3.8251,   -4.701,  -5.0772,  -5.0772,  -5.0603,  -3.7523,  -5.1989,  -4.3339,  -5.1345,  -5.1383,  -5.2743,  -5.1989,  -5.1626,  -5.1345,  -5.1989,  -5.1626,  -5.0818,  -4.8082,  -4.9947,  -4.8549,  -5.2743,  -5.1663,  -4.5719,    -4.59,  -4.6684,  -3.7859,  -4.5166,  -5.1383,  -5.1383,  -5.0818,  -5.1989,  -5.1477,  -5.1345,  -4.6498,  -4.8022,  -5.1383,  -5.1935,  -5.1345,  -5.1345,  -5.0697,  -5.2743,  -5.2743,  -5.1626,  -5.1345,  -5.1477,  -4.1093,  -5.2743,  -4.7901,  -5.1383,  -4.3058,  -5.1345,  -5.0878,  -4.6404,  -5.0878,  -5.1935,  -5.0818,  -4.8867,  -5.1663,  -5.1663,  -5.1626,  -5.1477,  -5.0878,  -5.0603,  -5.1663,  -4.6799,  -4.8082,  -5.1663,  -5.1663,  -5.1935,  -5.1383,  -5.0772,  -4.8589,  -5.1935,  -5.1477,  -5.1663,  -5.1477,  -5.0878,  -5.0818,  -5.0878,  -5.1935,  -5.1989,  -5.0818,  -5.3567,  -5.3567,  -5.3399,  -5.3399,  -5.2743,  -5.2743,  -5.2743,   -5.583,  -5.5557,  -5.5557,  -5.5557,   -5.552,   -5.552,   -5.552,   -5.552,   -5.552,   -5.552,  -5.1345,  -5.1345,  -5.5557,  -5.5557,  -5.5557,  -5.5557,  -5.5557,  -5.5371,  -5.5371,  -5.5371,  -5.5371,  -5.5371,  -5.4713,  -5.4713,  -5.4713,  -5.4713,  -5.4592,  -5.4592,  -5.4773,  -5.4773,  -5.4773,  -5.4773 ],
"loglift": [       30,       29,       28,       27,       26,       25,       24,       23,       22,       21,       20,       19,       18,       17,       16,       15,       14,       13,       12,       11,       10,        9,        8,        7,        6,        5,        4,        3,        2,        1,   2.4935,    2.424,   2.3196,   2.2766,   2.2646,   2.2611,   2.2329,   2.2329,   2.1991,    2.181,   2.1641,   2.1544,   2.1544,   2.1544,   2.1175,   2.0642,   2.0556,   2.0454,    2.017,    2.017,    2.017,   1.9429,   1.9371,   1.9199,   1.9051,   1.9049,    1.872,   1.8681,   1.7796,   1.7545,   2.4896,    2.485,    2.416,   2.4099,    2.392,    2.392,   2.3294,   2.3294,   2.2939,   2.2776,   2.2775,    2.268,   2.2434,   2.2434,   2.2434,   2.2107,   2.1993,   2.1982,   2.1654,   2.1654,   2.0804,   2.0773,   2.0288,   2.0288,   2.0259,   1.9558,    1.907,    1.904,   1.7988,   1.7917,   2.4053,   2.4053,   2.4053,   2.3594,   2.3549,   2.3522,   2.3233,   2.2914,   2.2882,   2.2882,   2.2882,   2.2744,   2.2635,   2.2601,   2.2527,   2.2248,   2.2062,   2.1984,   2.1623,   2.1623,   2.1623,   2.1623,   2.1623,   2.1623,   2.1623,   2.1623,   2.1623,   2.1623,   2.1623,   2.1623,   2.5936,   2.4809,   2.4115,   2.4115,   2.4115,   2.3844,   2.3754,   2.3754,   2.2448,   2.2448,   2.2448,   2.2441,   2.1599,   2.1556,   2.1416,   2.1099,   2.1062,   2.1062,   2.1062,   2.1062,   2.1062,   2.1062,   2.1062,   2.0336,   2.0301,   2.0301,    2.026,   2.0217,   1.9208,   1.8605,   2.5956,   2.5295,    2.463,    2.463,   2.4378,   2.4038,   2.4038,   2.3552,   2.3117,     2.28,     2.28,    2.194,   2.1746,   2.1478,   2.1478,   2.1478,   2.1478,   2.1478,   2.1478,   2.1478,   2.1478,   2.1478,   2.0878,   2.0773,   2.0743,   2.0436,    2.025,   2.0196,   1.9229,   1.8914,   2.5407,   2.5401,   2.4655,   2.4423,   2.4058,   2.4058,   2.3568,   2.3568,   2.3568,   2.3461,   2.2811,   2.2811,   2.2811,   2.2811,   2.2587,   2.2007,   2.1813,    2.148,    2.148,    2.148,    2.148,    2.148,    2.148,    2.148,    2.148,    2.148,    2.148,    2.148,    2.148,   2.1156,   2.5194,   2.5041,   2.4322,   2.4274,   2.4259,   2.4259,   2.3275,   2.3028,   2.3028,   2.3028,   2.2775,   2.2206,   2.2171,   2.2087,   2.2039,   2.1732,   2.1712,   2.1712,   2.1712,   2.1712,   2.1712,   2.1712,   2.1712,   2.1712,    2.147,   2.0935,   2.0884,   1.9476,   1.9297,   1.9297,   2.4818,   2.4282,   2.3799,   2.3799,   2.3053,   2.3053,   2.2929,   2.2113,    2.181,   2.1738,   2.1738,   2.1738,   2.1738,   2.1738,   2.1738,   2.1738,   2.1738,   2.1738,   2.1738,   2.1738,   2.1738,   2.1738,   2.1019,   2.0999,   2.0912,   2.0835,   2.0408,   1.9644,   1.9548,     1.94,   2.4723,   2.4723,   2.4723,   2.4391,   2.4391,   2.4253,   2.3917,    2.384,   2.3417,   2.3183,   2.3183,   2.2244,    2.221,   2.2175,    2.189,    2.189,    2.189,    2.189,    2.189,    2.189,    2.189,    2.189,    2.189,    2.189,    2.189,    2.189,   2.1164,   2.0751,    2.049,   1.9597,   2.5513,   2.4357,    2.434,   2.3852,   2.3852,   2.3774,    2.349,   2.3098,   2.3098,   2.3098,   2.3098,   2.3015,   2.2867,   2.2848,   2.1859,   2.1773,   2.1773,   2.1773,   2.1773,   2.1773,   2.1773,   2.1773,   2.1773,   2.1773,   2.1036,   1.9402,   1.9345,   1.9311,   1.9216,    1.913,   2.5965,   2.4977,    2.444,   2.3957,   2.2395,   2.2295,   2.1894,   2.1894,   2.1894,   2.1894,   2.1894,   2.1894,   2.1894,   2.1894,   2.1894,   2.1894,   2.1894,   2.1894,   2.1894,   2.1894,   2.1788,   2.1275,   2.1174,   2.1159,   2.0708,   2.0339,   1.9738,   1.9559,    1.948,    1.948,   2.6354,   2.6326,   2.5076,   2.4966,   2.3564,   2.3564,   2.3564,   2.2774,   2.2747,   2.2648,    2.229,    2.229,    2.229,    2.229,    2.229,    2.229,    2.229,    2.229,    2.227,    2.153,   2.1529,   2.1458,   2.1025,   2.0099,   1.9932,   1.9925,   1.9786,   1.9767,   1.9767,   1.9767,   2.4828,   2.4321,   2.4002,   2.3647,   2.3647,   2.3647,   2.3647,   2.3346,    2.303,   2.2689,   2.2378,   2.2378,   2.2378,   2.2378,   2.2378,   2.2378,   2.2378,   2.2378,   2.2378,   2.2238,   2.1691,   2.1674,   2.1659,   2.1452,   2.0867,   2.0002,   2.0001,   1.9902,   1.9866,   1.9814,    2.563,   2.5441,   2.5196,   2.4924,    2.439,   2.4267,   2.3656,   2.3656,   2.2406,   2.2361,   2.2361,   2.2361,   2.2361,   2.2361,   2.2361,   2.2361,   2.2361,   2.2361,   2.2361,   2.2361,   2.2361,   2.2361,   2.2361,   2.2361,   2.1666,   2.1366,    1.995,   1.9836,   1.9809,   1.9418,   1.8784,   1.9275,   2.1524,   2.1302,   1.9038,   1.8571,   1.9052,    1.895,   1.7088,   1.9782,   1.7256,   1.8515,    2.094,   2.0841,    1.838,   2.0923,    2.091,   2.0755,   2.0212,   2.0698,   1.7942,   1.8845,   1.8005,   1.7955,   1.3315,   1.7956,   1.7172,   1.7362,   1.3035,   1.9559,   1.8565,   1.8699,   1.8923,   1.5287,   1.8534,    1.487,    1.644,   1.3401,   1.6351,   1.1352,    1.743,   1.6463,   1.6437,   1.6642,    1.092,   1.9195,   1.4625,   1.9536,   1.9196,   1.8587,    1.907,   1.9304,   1.9426,   1.8886,   1.9167,   1.7253,   1.7942,   1.6436,   1.7424,   1.8337,   1.6484,   1.5094,   1.5769,   1.4919,   0.8656,    1.199,   1.7833,   1.7759,   1.6023,   1.7579,   1.7862,   1.7797,   1.2344,   1.1353,    1.665,   1.6457,   1.6825,   1.6823,   1.7418,   1.5817,   1.5731,   1.6445,   1.6726,   1.6631,   0.4347,   1.5616,   1.2992,   1.5826,   0.3457,     1.59,   1.6356,   0.7683,   1.6176,   1.5097,   1.3505,   0.9986,   1.4361,   1.4311,   1.4492,   1.4564,   1.4678,   1.3812,   1.3817,   0.2804,   0.8047,   1.2661,   1.2288,   1.1594,   1.0964,   1.1144,   0.3698,   0.9733,     0.98,    0.883,   0.8276,   0.9081,   0.8124,   0.7086,   0.5318,   0.5264,   0.5277,   1.6318,   1.6067,   1.0552,   1.6318,   1.1208,    -0.43,   0.9854,   0.6412,   1.7111,   1.9129,    1.053,   1.7031,   1.0863,   1.5178,    1.304,   1.5417,   1.1719,   0.4481,   1.5496,   1.0826,    1.053,    1.056,   0.3818,   1.5336,   1.5521,   1.9331,   1.4451,     1.92,   1.5782,   1.0352,   1.7761,   1.4922,   1.7984,   0.1503,   1.6189,  -0.0685,   1.8051,    1.774,   1.0335 ],
"Freq": [       66,       54,       43,       59,       44,       53,       39,       26,       26,       22,       28,       20,       30,       17,       16,       21,       20,       20,       25,       18,       18,       14,       15,       14,       13,       13,       15,       12,       17,       10,  52.9277, 8.992904, 4.187535,  16.5442, 15.85772, 15.85772, 2.814573, 2.814573, 6.246979, 4.187535, 5.560498, 2.128092, 2.128092, 2.128092, 4.874016, 2.814573, 2.814573, 2.814573, 1.441611, 1.441611, 1.441611, 2.128092, 2.128092, 2.814573, 2.814573, 2.814573, 4.187535, 4.187535, 2.128092, 1.441611, 21.53836, 19.46071, 7.687325, 13.22774, 6.302222, 6.302222, 4.224566, 4.224566, 3.532014, 10.45753,  5.60967,  5.60967, 2.839463, 2.839463, 2.839463, 8.379877, 4.224566, 4.224566, 2.146911, 2.146911, 4.224566, 15.99795, 1.454359, 1.454359, 36.08195, 2.146911, 2.839463, 2.839463, 2.146911, 2.839463, 3.964241, 3.964241, 3.964241, 3.186939, 5.518846, 10.18266, 4.741543, 6.296148, 2.409637, 2.409637, 2.409637, 3.964241, 3.964241, 5.518846, 5.518846, 12.51457, 4.741543,  7.07345, 1.632335, 1.632335, 1.632335, 1.632335, 1.632335, 1.632335, 1.632335, 1.632335, 1.632335, 1.632335, 1.632335, 1.632335, 65.19376, 11.60055, 4.138209, 4.138209, 4.138209, 12.27895, 3.459814, 3.459814, 2.103024, 2.103024, 2.103024, 6.851789, 4.138209, 5.494999, 2.781419, 4.816604, 1.424629, 1.424629, 1.424629, 1.424629, 1.424629, 1.424629, 1.424629, 2.103024, 2.103024, 2.103024, 2.103024, 2.103024, 5.494999, 2.781419, 25.47911, 8.783398, 5.153894, 5.153894, 4.427994, 3.702093, 3.702093, 2.976193, 4.427994, 2.250292, 2.250292, 2.976193, 2.976193, 1.524391, 1.524391, 1.524391, 1.524391, 1.524391, 1.524391, 1.524391, 1.524391, 1.524391, 2.250292, 2.250292, 2.250292,  16.7683, 3.702093, 8.057497, 3.702093, 1.524391,  24.5203,  9.41982, 5.105399, 11.57703, 3.667258, 3.667258, 2.948188, 2.948188, 2.948188, 5.105399, 2.229118, 2.229118, 2.229118, 2.229118, 3.667258, 5.824469, 2.948188, 1.510048, 1.510048, 1.510048, 1.510048, 1.510048, 1.510048, 1.510048, 1.510048, 1.510048, 1.510048, 1.510048, 1.510048, 3.667258, 6.649284, 5.918594, 6.649284, 6.649284, 3.726522, 3.726522, 4.457213, 2.265141, 2.265141, 2.265141, 3.726522, 4.457213, 2.995831, 2.995831, 2.995831, 5.187903,  1.53445,  1.53445,  1.53445,  1.53445,  1.53445,  1.53445,  1.53445,  1.53445, 5.918594, 2.265141, 2.265141, 2.265141,  1.53445,  1.53445, 8.856939,  3.73309, 3.001112, 3.001112, 2.269133, 2.269133,  3.73309, 3.001112, 5.197047, 1.537155, 1.537155, 1.537155, 1.537155, 1.537155, 1.537155, 1.537155, 1.537155, 1.537155, 1.537155, 1.537155, 1.537155, 1.537155, 2.269133, 7.392982, 2.269133, 8.856939,  3.73309, 3.001112, 4.465069, 3.001112, 4.564242, 4.564242, 4.564242, 3.816006, 3.816006, 9.053661, 3.067769, 5.312479, 4.564242, 2.319533, 2.319533, 3.067769, 3.067769, 3.067769, 1.571297, 1.571297, 1.571297, 1.571297, 1.571297, 1.571297, 1.571297, 1.571297, 1.571297, 1.571297, 1.571297, 1.571297, 2.319533, 3.067769, 5.312479, 3.067769, 8.027314, 6.580951, 3.688225, 2.965044, 2.965044, 5.134588, 4.411407, 2.241863, 2.241863, 2.241863, 2.241863, 7.304133, 30.44594, 8.750496, 17.42867, 1.518681, 1.518681, 1.518681, 1.518681, 1.518681, 1.518681, 1.518681, 1.518681, 1.518681, 2.241863, 2.965044, 1.518681, 2.241863, 1.518681, 2.241863, 40.28388, 8.846368, 3.728635,  2.99753, 4.459739, 4.459739,  1.53532,  1.53532,  1.53532,  1.53532,  1.53532,  1.53532,  1.53532,  1.53532,  1.53532,  1.53532,  1.53532,  1.53532,  1.53532,  1.53532, 9.577473, 2.266425, 2.266425, 5.190844, 3.728635, 5.190844,  2.99753, 2.266425,  1.53532,  1.53532, 16.12618, 15.36191, 4.662071, 7.719167, 2.369249, 2.369249, 2.369249, 4.662071, 3.133523, 3.133523, 1.604975, 1.604975, 1.604975, 1.604975, 1.604975, 1.604975, 1.604975, 1.604975, 7.719167, 2.369249, 2.369249, 2.369249, 3.897797, 2.369249, 1.604975, 2.369249, 1.604975, 1.604975, 1.604975, 1.604975, 3.919209, 5.456154, 4.687681, 2.382264, 2.382264, 2.382264, 2.382264, 3.919209,  12.3724, 3.150737, 1.613792, 1.613792, 1.613792, 1.613792, 1.613792, 1.613792, 1.613792, 1.613792, 1.613792, 3.919209, 2.382264, 2.382264, 2.382264, 3.150737, 7.761571, 1.613792, 2.382264, 1.613792, 1.613792, 2.382264, 6.055582,  5.30798, 4.560377, 6.803185, 3.065171, 7.550788, 2.317569, 2.317569, 24.74565, 1.569966, 1.569966, 1.569966, 1.569966, 1.569966, 1.569966, 1.569966, 1.569966, 1.569966, 1.569966, 1.569966, 1.569966, 1.569966, 1.569966, 1.569966, 2.317569, 3.065171, 1.569966, 1.569966, 1.569966, 0.822363, 8.057497, 2.265141, 3.964241,  7.07345, 5.187903, 24.22849, 5.190844, 3.065171, 3.501054,  7.26261, 3.532014, 3.812774, 2.409637, 2.229118,  2.99753, 2.409637, 2.409637, 2.229118, 2.948188, 2.229118, 3.728635, 2.382264, 3.065171, 5.153894, 15.36191, 3.065171, 2.965044, 4.459739, 13.95619, 3.067769, 2.382264, 3.816006, 2.948188, 9.053661, 2.382264, 4.187535, 4.138209, 7.761571, 3.919209, 9.764981, 3.667258, 2.814573, 2.814573, 2.839463, 9.509298, 2.229118, 5.197047, 2.319533, 2.409637, 2.103024, 2.229118, 2.269133, 2.319533, 2.229118, 2.269133, 2.369249, 3.065171, 2.781419, 3.067769, 2.103024, 2.241863, 3.919209, 3.812774, 3.726522, 8.846368, 4.427994, 2.409637, 2.409637, 2.369249, 2.229118, 2.266425, 2.319533, 3.728635, 3.133523, 2.409637, 2.250292, 2.319533, 2.319533, 2.382264, 2.103024, 2.103024, 2.269133, 2.319533, 2.266425, 6.224626, 2.103024, 3.150737, 2.409637, 5.312479, 2.319533, 2.317569, 3.964241, 2.317569, 2.250292, 2.369249, 2.995831, 2.265141, 2.265141, 2.269133, 2.266425, 2.317569, 2.839463, 2.241863, 4.187535, 3.065171, 2.241863, 2.241863, 2.250292, 2.409637, 2.814573, 3.501054, 2.250292, 2.266425, 2.241863, 2.266425, 2.317569, 2.369249, 2.317569, 2.250292, 2.229118, 2.369249, 2.128092, 2.128092, 2.146911, 2.146911, 2.103024, 2.103024, 2.103024, 1.524391,  1.53445,  1.53445,  1.53445, 1.537155, 1.537155, 1.537155, 1.537155, 1.537155, 1.537155, 2.319533, 2.319533, 1.518681, 1.518681, 1.518681, 1.518681, 1.518681,  1.53532,  1.53532,  1.53532,  1.53532,  1.53532, 1.604975, 1.604975, 1.604975, 1.604975, 1.613792, 1.613792, 1.569966, 1.569966, 1.569966, 1.569966 ],
"Total": [       66,       54,       43,       59,       44,       53,       39,       26,       26,       22,       28,       20,       30,       17,       16,       21,       20,       20,       25,       18,       18,       14,       15,       14,       13,       13,       15,       12,       17,       10, 54.60748,  9.94678, 5.141411, 21.20416, 20.57048, 20.64136, 3.768449, 3.768449, 8.651904, 5.905685, 7.975755, 3.081968, 3.081968, 3.081968, 7.324365, 4.461001, 4.499554, 4.545751, 2.395487, 2.395487, 2.395487, 3.807868, 3.830204, 5.153553, 5.230659, 5.231532, 8.043976,  8.07523, 4.483544, 3.114557, 22.49163, 20.41398, 8.640594, 14.95831, 7.255491, 7.255491, 5.177835, 5.177835, 4.485283,  13.4987, 7.241334, 7.310542, 3.792732, 3.792732, 3.792732,  11.5654, 5.896906, 5.903736,  3.10018,  3.10018, 6.641792, 25.22906, 2.407628, 2.407628, 59.90662, 3.823361,  5.30944, 5.325478, 4.473142, 5.958165, 4.909035, 4.909035, 4.909035, 4.131733, 7.186821,   13.297, 6.372819, 8.737194, 3.354431, 3.354431, 3.354431, 5.595516, 5.656638,  7.90178, 7.960112, 18.56237, 7.164631,  10.7725, 2.577129, 2.577129, 2.577129, 2.577129, 2.577129, 2.577129, 2.577129, 2.577129, 2.577129, 2.577129, 2.577129, 2.577129, 66.87163, 13.31951, 5.092894, 5.092894, 5.092894, 15.52646, 4.414499, 4.414499, 3.057709, 3.057709, 3.057709,  9.96888, 6.549485, 8.734232, 4.483707, 8.014097, 2.379314, 2.379314, 2.379314, 2.379314, 2.379314, 2.379314, 2.379314, 3.776779, 3.789688, 3.789688, 3.805312, 3.821983,  11.0459, 5.938867, 26.42905, 9.733332, 6.103829, 6.103829, 5.377928, 4.652027, 4.652027, 3.926127, 6.101109, 3.200226, 3.200226, 4.612608, 4.703429, 2.474325, 2.474325, 2.474325, 2.474325, 2.474325, 2.474325, 2.474325, 2.474325, 2.474325, 3.878621, 3.919296, 3.931331, 30.20631, 6.794206, 14.86768,  7.52507, 3.197507, 26.98019, 10.37044, 6.056016,  14.0562, 4.617875, 4.617875, 3.898805, 3.898805, 3.898805, 6.824488, 3.179735, 3.179735, 3.179735, 3.179735, 5.349854, 9.003538, 4.647042, 2.460665, 2.460665, 2.460665, 2.460665, 2.460665, 2.460665, 2.460665, 2.460665, 2.460665, 2.460665, 2.460665, 2.460665,  6.17248, 7.598739, 6.868049, 8.291291, 8.330718, 4.675977, 4.675977, 6.170942, 3.214596, 3.214596, 3.214596, 5.424214, 6.867692, 4.631768, 4.671187, 4.693523,   8.3808, 2.483905, 2.483905, 2.483905, 2.483905, 2.483905, 2.483905, 2.483905, 2.483905, 9.815056, 3.962832, 3.983068, 4.585543,   3.1623,   3.1623, 10.52945, 4.682416, 3.950438, 3.950438,  3.21846,  3.21846, 5.360811, 4.676339, 8.346918, 2.486481, 2.486481, 2.486481, 2.486481, 2.486481, 2.486481, 2.486481, 2.486481, 2.486481, 2.486481, 2.486481, 2.486481, 2.486481,  3.94436, 12.87722, 3.986932, 15.68206,  6.89796, 5.985623, 8.991213, 6.133392, 5.511943, 5.511943, 5.511943, 4.763707, 4.763707, 11.45924,  4.01547, 7.007782, 6.280415, 3.267234, 3.267234, 4.746575, 4.763073, 4.779744, 2.518997, 2.518997, 2.518997, 2.518997, 2.518997, 2.518997, 2.518997, 2.518997, 2.518997, 2.518997, 2.518997, 2.518997, 3.998338, 5.510849, 9.795548, 6.185014,  8.97752, 8.261848, 4.638432,  3.91525,  3.91525, 6.833031, 6.040008, 3.192069, 3.192069, 3.192069, 3.192069, 10.48734, 44.36451, 12.77459,  28.0897, 2.468887, 2.468887, 2.468887, 2.468887, 2.468887, 2.468887, 2.468887, 2.468887, 2.468887, 3.923173, 6.109438, 3.147282, 4.661923, 3.187957, 4.746673, 43.39461, 10.51896, 4.678048, 3.946944,  6.86485, 6.934058, 2.484734, 2.484734, 2.484734, 2.484734, 2.484734, 2.484734, 2.484734, 2.484734, 2.484734, 2.484734, 2.484734, 2.484734, 2.484734, 2.484734, 15.66519,  3.90232, 3.941739, 9.042182, 6.794584, 9.814433, 6.018528,  4.63301, 3.163129, 3.163129, 17.07228,   16.308, 5.608168, 9.388446, 3.315346, 3.315346, 3.315346, 7.059969, 4.758015, 4.805521, 2.551072, 2.551072, 2.551072, 2.551072, 2.551072, 2.551072, 2.551072, 2.551072,  12.2933, 4.062949, 4.063583, 4.092648, 7.031033, 4.688309, 3.229467, 4.770506, 3.276973, 3.283051, 3.283051, 3.283051, 4.864886, 7.125012,  6.31984, 3.327941, 3.327941, 3.327941, 3.327941, 5.642188, 18.38369, 4.844016, 2.559469, 2.559469, 2.559469, 2.559469, 2.559469, 2.559469, 2.559469, 2.559469, 2.559469, 6.303026, 4.047012, 4.053842,  4.05992, 5.481517,  14.3168,  3.24595, 4.791898, 3.278539,  3.29016, 4.882546, 7.003346, 6.255744, 5.508141, 8.443501, 4.012935, 10.00783, 3.265333, 3.265333, 39.50803,  2.51773,  2.51773,  2.51773,  2.51773,  2.51773,  2.51773,  2.51773,  2.51773,  2.51773,  2.51773,  2.51773,  2.51773,  2.51773,  2.51773,  2.51773, 3.984403, 5.430107, 3.204211, 3.240911, 3.249708, 1.770127, 17.12232, 4.678553, 6.321417, 11.53264,   10.972, 53.79775, 11.16239, 6.913819, 7.917689, 14.02492, 7.917689, 8.982547, 4.073501, 3.872287, 6.894172, 4.080331, 4.085536, 3.905636,  5.45341, 3.927971, 8.959881, 5.379299, 7.599074, 11.89872, 59.90662, 7.636352, 7.636352, 11.35591, 53.79775, 6.208785, 5.531875, 8.417012, 6.204222,  28.0897, 5.549041,  11.8214,   10.972, 30.20631, 11.35591, 39.50803, 8.959881, 6.775531, 6.792907, 6.768546, 44.36451, 4.564839, 17.12232, 4.705374, 4.849636, 4.498497, 4.622404, 4.682243, 4.757408, 4.708283, 4.747008,  6.23153, 7.647259, 7.377115, 7.686249, 4.612314, 6.185014, 12.87722,  11.8214, 11.89872, 53.79775, 18.56237, 5.557621,  5.59914, 7.047598, 5.365793, 5.489513,  5.59914, 15.68206, 14.86768, 6.255941, 6.035091, 6.170692, 6.171476, 6.204222, 5.934048, 5.985623, 6.231641, 6.231641, 6.208785, 59.90662, 6.054666, 12.77459, 6.792907, 53.79775, 6.768546, 6.775531, 25.22906,  6.89862, 6.913819, 9.064882, 15.66519, 7.647259, 7.686249, 7.576217,  7.63436, 8.014097, 8.982547,  8.07523, 39.50803, 20.57048, 9.064882, 9.408976, 9.814433,  11.0459, 11.53264, 30.20631,  11.8214,  12.2933,   13.297,  14.3168, 14.02492, 15.52646, 17.12232, 18.38369, 18.38369, 20.64136, 5.197762, 5.329586, 9.408976, 5.286238, 9.408976, 44.36451,  10.7725, 11.16239, 3.934954, 3.215884, 7.599074, 3.981446, 7.377115, 4.791898, 5.934048, 4.678553, 6.772455, 21.20416, 7.047598, 7.377115, 7.599074, 7.576217, 14.86768, 4.699569, 4.699569, 3.210634, 5.230659, 3.253206, 4.578862, 8.417012, 4.012453, 5.329586, 3.924035, 20.64136, 4.752369, 25.22906,  3.87452, 3.996657,   8.3808 ],
"Category": [ "Default", "Default", "Default", "Default", "Default", "Default", "Default", "Default", "Default", "Default", "Default", "Default", "Default", "Default", "Default", "Default", "Default", "Default", "Default", "Default", "Default", "Default", "Default", "Default", "Default", "Default", "Default", "Default", "Default", "Default", "Topic1", "Topic1", "Topic1", "Topic1", "Topic1", "Topic1", "Topic1", "Topic1", "Topic1", "Topic1", "Topic1", "Topic1", "Topic1", "Topic1", "Topic1", "Topic1", "Topic1", "Topic1", "Topic1", "Topic1", "Topic1", "Topic1", "Topic1", "Topic1", "Topic1", "Topic1", "Topic1", "Topic1", "Topic1", "Topic1", "Topic2", "Topic2", "Topic2", "Topic2", "Topic2", "Topic2", "Topic2", "Topic2", "Topic2", "Topic2", "Topic2", "Topic2", "Topic2", "Topic2", "Topic2", "Topic2", "Topic2", "Topic2", "Topic2", "Topic2", "Topic2", "Topic2", "Topic2", "Topic2", "Topic2", "Topic2", "Topic2", "Topic2", "Topic2", "Topic2", "Topic3", "Topic3", "Topic3", "Topic3", "Topic3", "Topic3", "Topic3", "Topic3", "Topic3", "Topic3", "Topic3", "Topic3", "Topic3", "Topic3", "Topic3", "Topic3", "Topic3", "Topic3", "Topic3", "Topic3", "Topic3", "Topic3", "Topic3", "Topic3", "Topic3", "Topic3", "Topic3", "Topic3", "Topic3", "Topic3", "Topic4", "Topic4", "Topic4", "Topic4", "Topic4", "Topic4", "Topic4", "Topic4", "Topic4", "Topic4", "Topic4", "Topic4", "Topic4", "Topic4", "Topic4", "Topic4", "Topic4", "Topic4", "Topic4", "Topic4", "Topic4", "Topic4", "Topic4", "Topic4", "Topic4", "Topic4", "Topic4", "Topic4", "Topic4", "Topic4", "Topic5", "Topic5", "Topic5", "Topic5", "Topic5", "Topic5", "Topic5", "Topic5", "Topic5", "Topic5", "Topic5", "Topic5", "Topic5", "Topic5", "Topic5", "Topic5", "Topic5", "Topic5", "Topic5", "Topic5", "Topic5", "Topic5", "Topic5", "Topic5", "Topic5", "Topic5", "Topic5", "Topic5", "Topic5", "Topic5", "Topic6", "Topic6", "Topic6", "Topic6", "Topic6", "Topic6", "Topic6", "Topic6", "Topic6", "Topic6", "Topic6", "Topic6", "Topic6", "Topic6", "Topic6", "Topic6", "Topic6", "Topic6", "Topic6", "Topic6", "Topic6", "Topic6", "Topic6", "Topic6", "Topic6", "Topic6", "Topic6", "Topic6", "Topic6", "Topic6", "Topic7", "Topic7", "Topic7", "Topic7", "Topic7", "Topic7", "Topic7", "Topic7", "Topic7", "Topic7", "Topic7", "Topic7", "Topic7", "Topic7", "Topic7", "Topic7", "Topic7", "Topic7", "Topic7", "Topic7", "Topic7", "Topic7", "Topic7", "Topic7", "Topic7", "Topic7", "Topic7", "Topic7", "Topic7", "Topic7", "Topic8", "Topic8", "Topic8", "Topic8", "Topic8", "Topic8", "Topic8", "Topic8", "Topic8", "Topic8", "Topic8", "Topic8", "Topic8", "Topic8", "Topic8", "Topic8", "Topic8", "Topic8", "Topic8", "Topic8", "Topic8", "Topic8", "Topic8", "Topic8", "Topic8", "Topic8", "Topic8", "Topic8", "Topic8", "Topic8", "Topic9", "Topic9", "Topic9", "Topic9", "Topic9", "Topic9", "Topic9", "Topic9", "Topic9", "Topic9", "Topic9", "Topic9", "Topic9", "Topic9", "Topic9", "Topic9", "Topic9", "Topic9", "Topic9", "Topic9", "Topic9", "Topic9", "Topic9", "Topic9", "Topic9", "Topic9", "Topic9", "Topic9", "Topic9", "Topic9", "Topic10", "Topic10", "Topic10", "Topic10", "Topic10", "Topic10", "Topic10", "Topic10", "Topic10", "Topic10", "Topic10", "Topic10", "Topic10", "Topic10", "Topic10", "Topic10", "Topic10", "Topic10", "Topic10", "Topic10", "Topic10", "Topic10", "Topic10", "Topic10", "Topic10", "Topic10", "Topic10", "Topic10", "Topic10", "Topic10", "Topic11", "Topic11", "Topic11", "Topic11", "Topic11", "Topic11", "Topic11", "Topic11", "Topic11", "Topic11", "Topic11", "Topic11", "Topic11", "Topic11", "Topic11", "Topic11", "Topic11", "Topic11", "Topic11", "Topic11", "Topic11", "Topic11", "Topic11", "Topic11", "Topic11", "Topic11", "Topic11", "Topic11", "Topic11", "Topic11", "Topic12", "Topic12", "Topic12", "Topic12", "Topic12", "Topic12", "Topic12", "Topic12", "Topic12", "Topic12", "Topic12", "Topic12", "Topic12", "Topic12", "Topic12", "Topic12", "Topic12", "Topic12", "Topic12", "Topic12", "Topic12", "Topic12", "Topic12", "Topic12", "Topic12", "Topic12", "Topic12", "Topic12", "Topic12", "Topic12", "Topic13", "Topic13", "Topic13", "Topic13", "Topic13", "Topic13", "Topic13", "Topic13", "Topic13", "Topic13", "Topic13", "Topic13", "Topic13", "Topic13", "Topic13", "Topic13", "Topic13", "Topic13", "Topic13", "Topic13", "Topic13", "Topic13", "Topic13", "Topic13", "Topic13", "Topic13", "Topic13", "Topic13", "Topic13", "Topic13", "Topic14", "Topic14", "Topic14", "Topic14", "Topic14", "Topic14", "Topic14", "Topic14", "Topic14", "Topic14", "Topic14", "Topic14", "Topic14", "Topic14", "Topic14", "Topic14", "Topic14", "Topic14", "Topic14", "Topic14", "Topic14", "Topic14", "Topic14", "Topic14", "Topic14", "Topic14", "Topic14", "Topic14", "Topic14", "Topic14", "Topic5", "Topic7", "Topic3", "Topic3", "Topic7", "Topic8", "Topic11", "Topic14", "Topic1", "Topic6", "Topic2", "Topic14", "Topic3", "Topic6", "Topic11", "Topic3", "Topic3", "Topic6", "Topic6", "Topic6", "Topic11", "Topic13", "Topic14", "Topic5", "Topic12", "Topic14", "Topic10", "Topic11", "Topic7", "Topic9", "Topic13", "Topic9", "Topic6", "Topic9", "Topic13", "Topic1", "Topic4", "Topic13", "Topic13", "Topic2", "Topic6", "Topic1", "Topic1", "Topic2", "Topic5", "Topic6", "Topic8", "Topic9", "Topic3", "Topic4", "Topic6", "Topic8", "Topic9", "Topic6", "Topic8", "Topic12", "Topic14", "Topic4", "Topic9", "Topic4", "Topic10", "Topic13", "Topic14", "Topic7", "Topic11", "Topic5", "Topic3", "Topic3", "Topic12", "Topic6", "Topic11", "Topic9", "Topic11", "Topic12", "Topic3", "Topic5", "Topic9", "Topic9", "Topic13", "Topic4", "Topic4", "Topic8", "Topic9", "Topic11", "Topic13", "Topic4", "Topic13", "Topic3", "Topic9", "Topic9", "Topic14", "Topic3", "Topic14", "Topic5", "Topic12", "Topic7", "Topic7", "Topic7", "Topic8", "Topic11", "Topic14", "Topic2", "Topic10", "Topic1", "Topic14", "Topic10", "Topic10", "Topic5", "Topic3", "Topic1", "Topic1", "Topic5", "Topic11", "Topic10", "Topic11", "Topic14", "Topic12", "Topic14", "Topic5", "Topic6", "Topic12", "Topic1", "Topic1", "Topic2", "Topic2", "Topic4", "Topic4", "Topic4", "Topic5", "Topic7", "Topic7", "Topic7", "Topic8", "Topic8", "Topic8", "Topic8", "Topic8", "Topic8", "Topic9", "Topic9", "Topic10", "Topic10", "Topic10", "Topic10", "Topic10", "Topic11", "Topic11", "Topic11", "Topic11", "Topic11", "Topic12", "Topic12", "Topic12", "Topic12", "Topic13", "Topic13", "Topic14", "Topic14", "Topic14", "Topic14" ] 
},
"token.table": {
 "Term": [ "abstract", "abstract", "abstract", "acquisition", "acquisition", "across", "additional", "additional", "additive", "admitted", "admitted", "advances", "aims", "algebra", "algebraic", "algebraic", "algorithm", "algorithm", "algorithm", "algorithmic", "algorithmic", "algorithmic", "algorithms", "algorithms", "algorithms", "already", "analyses", "analysis", "analysis", "analysis", "analysis", "analysis", "analytics", "analytics", "analytics", "analytics", "analyze", "analyze", "analyzing", "analyzing", "application", "application", "application", "application", "applications", "applications", "applications", "applied", "apply", "apply", "apply", "approach", "approaches", "approaches", "approximation", "approximations", "approximations", "area", "articles", "articles", "assessment", "assessment", "assessment", "associated", "associated", "associated", "assumptions", "asymptotic", "automata", "automata", "available", "available", "average", "background", "background", "background", "balanced", "balanced", "based", "based", "based", "bases", "basis", "basis", "behind", "best", "bias", "bias", "big_data", "big_data", "binary", "biological", "biology", "bivariate", "block", "blocking", "bounds", "briefly", "build", "business", "business", "business", "calculus", "calculus", "cardinal", "carlo", "central", "certain", "certain", "chain", "chain", "chains", "chains", "challenging", "challenging", "change", "choice", "classification", "classification", "classification", "cleaning", "cleaning", "clustering", "code", "code", "collaboration", "collaboration", "collaborative", "collections", "combinations", "combinations", "combinatorial", "commercially", "communication", "communication", "communication", "community", "complete", "complete", "completion", "complex", "complexity", "complexity", "computation", "computation", "computation", "computation", "computational", "computational", "computational", "computer", "computer", "computer", "computer", "computer_science", "computers", "computers", "computing", "computing", "concurrency", "conditional", "confidence", "confidence", "consistency", "constraints", "construction", "construction", "context", "contexts", "continuity", "continuous", "continuous", "continuous", "contradiction", "control", "control", "control", "control", "convergence", "convergence", "correctness", "correctness", "counting", "counting", "counting", "critical", "curve", "cycle", "data_analysis", "data_analysis", "data_analysis", "data_analysis", "data_mining", "data_mining", "data_mining", "data_science", "data_science", "data_science", "data_science", "data_sets", "data_sets", "data_sets", "data_structures", "data_structures", "data_structures", "data_visualization", "data_visualization", "data_visualization", "database", "database_systems", "datasets", "debugging", "debugging", "debugging", "decision", "decision", "decision", "definite", "demonstrate", "density", "derivatives", "descriptive", "descriptive", "designed", "designed", "designing", "designs", "detail", "determinants", "develop", "developing", "diagonalization", "diagonalization", "dictionaries", "different", "different", "differential", "differential", "differential_equations", "differential_equations", "dimension", "dimension", "direct", "disciplines", "discovering", "discrete", "discrete", "discrete", "discriminant", "discusses", "discussion", "distribution", "distribution", "distributions", "distributions", "document", "documentation", "documents", "dot", "dynamic", "dynamic", "dynamic", "economics", "education", "efficiency", "efficiency", "eigenvalues", "eigenvectors", "eigenvectors", "electricity", "elimination", "emphasizing", "enable", "enable", "end", "engine", "engineering", "engines", "engines", "engl", "ensemble", "entrepreneurship", "environment", "environment", "environment", "equations", "equations", "error", "error", "error", "error", "estimating", "estimation", "estimation", "estimation", "estimator", "estimators", "evaluation", "evaluation", "evidence", "excel", "expectation", "expected", "expected", "experimental", "experimental", "experiments", "experiments", "explanatory", "exploration", "exploratory", "exploratory", "exposure", "expressions", "extended", "factorial", "factorial", "feedback", "field", "field", "field", "field", "fields", "files", "final", "final", "financial", "financial", "focus", "focus", "focus", "focused", "focusing", "following", "following", "following", "forecasting", "forecasting", "formal", "forms", "foundations", "foundations", "fourier", "fourier", "fulltime", "fulltime", "function", "functional", "fundamentals", "gaussian", "generalized", "generalized", "generalized", "generating", "generating", "generation", "geometric", "geometric", "given", "goodness", "grade", "grade", "grade", "gradient", "graph", "graph", "graph", "graph", "graph_theory", "graph_theory", "graph_theory", "graph_theory", "graphical", "graphical", "graphical", "graphs", "graphs", "graphs", "graphs", "graphs", "graphs", "greater", "greater", "greedy", "greedy", "handson", "handson", "hash", "hash", "heaps", "human", "human", "hypotheses", "hypothesis_testing", "hypothesis_testing", "hypothesis_testing", "ideas", "illustrated", "illustrated", "implementation", "implementation", "implementation", "implementation", "improvement", "independence", "independence", "indepth", "indexing", "induction", "induction", "induction", "induction", "inference", "information", "information", "inheritance", "inner", "integral", "integrals", "integrals", "integration", "integration", "integration", "integrity", "integrity", "interdisciplinary", "interdisciplinary", "interdisciplinary", "interpolation", "introduce", "investigate", "iterative", "iterative", "kernel", "knowledge", "knowledge", "lagrange", "lagrange", "law", "learn", "learn", "learn", "learn", "learning", "learning", "learning", "least", "least", "least", "least", "life", "likelihood", "likelihood", "likelihood", "likelihood", "limit", "limit", "limits", "limits", "limits", "linear", "linear", "linear", "linear_regression", "linear_regression", "lines", "lists", "lists", "lists", "logic", "logic", "logic", "logic", "machine_learning", "machine_learning", "machines", "magnetism", "main", "majors", "majors", "make", "make", "making", "making", "management", "management", "management", "manipulation", "maple", "marginal", "marketing", "marketing", "markov", "markov", "markov", "markov", "markov", "mathematics", "mathematics", "matrices", "matrices", "matrices", "matrix", "maximum", "maximum", "mean", "means", "means", "means", "measurement", "memory", "memory", "method", "method", "method", "mining", "mining", "mining", "mining", "modelling", "modelling", "modelling", "modelling", "models", "models", "moment", "monte", "monte", "multinomial", "multiple", "multiple", "multiple", "multipliers", "multivariable", "multivariate", "multivariate", "multivariate", "natural", "natural", "needed", "needed", "network", "network", "networks", "networks", "neural", "neural_networks", "neural_networks", "neural_networks", "nonhomogeneous", "nonlinear_regression", "notation", "notation", "notions", "numbers", "numbers", "numerical", "numerical", "numerical", "numerical", "objectoriented", "objectoriented", "observational", "observational", "observational", "offerings", "operating", "operations", "operations", "opportunity", "optics", "optimization", "optimization", "optimization", "optimization", "oral", "ordinary", "ordinary", "ordinary", "orthogonality", "overview", "overview", "packages", "parallel", "parallel", "parameters", "parameters", "parametric", "parametric", "parametric", "parametric", "partial", "partial", "particular", "passfail", "passfail", "patterns", "patterns", "patterns", "perspective", "placed", "planes", "planning", "planning", "point", "poisson", "poisson", "policy", "power", "power", "power", "practical", "practical", "practical", "practical", "precise", "prediction", "prediction", "predictive", "predictive", "predictive", "predictive", "preparation", "prerequisites", "presentation", "presentation", "presented", "primary", "privacy", "privacy", "probabilistic", "probabilistic", "probabilistic", "probability", "problem", "problem", "problems", "problems", "problems", "problems", "problemsolving", "problemsolving", "process", "process", "process", "processing", "processing", "processing", "processing", "professional", "professional", "programming", "programming", "programming", "programming", "project", "project", "project", "project", "proof", "proof", "proof", "proofs", "proofs", "proofs", "properties", "properties", "properties", "properties", "propositional", "provide", "provide", "public", "python", "python", "qualitative", "quantitative", "quantitative", "quantitative", "quantitative", "query", "query", "querying", "querying", "questions", "queues", "queues", "queues", "random", "randomization", "randomization", "rank", "ranking", "rates", "rather", "ratio", "reading", "reading", "realworld", "realworld", "records", "recurrence", "recursive", "recursive", "recursive", "reduction", "reduction", "regression", "regression", "regression", "regression_models", "regular", "regular", "regularization", "relational", "relationship", "relationship", "relevance", "relevant", "reliability", "reliability", "representation", "representation", "representation", "representation", "representation", "requirements", "research", "response", "response", "response", "ridge", "rigorous", "rigorous", "rigorous", "rigorous", "sample", "sample", "sample", "sample", "sample", "sample", "samples", "sampling", "sampling", "sampling", "sampling", "satisfy", "scale", "scheduling", "scripting", "scripting", "searching", "searching", "searching", "selection", "selection", "sequences", "series", "series", "set", "sets", "sets", "several", "several", "shell", "shell", "significant", "simple", "simple", "simple", "simplex", "simulation", "simulation", "simulation", "simulation", "simulation", "simulationbased", "skill", "skills", "skills", "software", "software", "software", "solution", "solution", "solving", "solving", "solving", "solving", "sorting", "sorting", "sorting", "space", "space", "spaces", "spaces", "specialist", "specialist", "specialist", "specialist", "specialist", "specializing", "specific", "specific", "specification", "specification", "splines", "sql", "squares", "squares", "squares", "squares", "state", "statistics", "statistics", "statistics", "statistics", "strategic", "strategies", "strategies", "strategies", "strong", "strong", "structure", "structures", "structures", "structures", "structures", "study", "study", "studying", "subset", "subspaces", "substituted", "subsystem", "supervised", "supervised", "supervised", "support", "surface", "surface", "surveys", "surveys", "symbolic", "symmetric", "system", "system", "system", "systems", "systems", "systems", "systems", "systems", "table", "taylor", "taylors", "teaches", "team", "team", "team", "teamwork", "technical", "technical", "technical", "technology", "technology", "term", "term", "test", "test", "testing", "testing", "tests", "text", "text", "text", "theorem", "theorem", "theorem", "theorems", "theorems", "theorems", "theorems", "theoretical", "theoretical", "theoretical", "theories", "theory", "theory", "theory", "theory", "theory", "theory", "time", "time", "time", "time", "time", "times", "times", "titles", "training", "transaction", "transcendental", "transform", "transformation", "transformations", "transforming", "transforms", "trees", "trees", "trees", "trees", "tutorial", "uncertainty", "understand", "unsupervised", "unsupervised", "upper", "upper", "useful", "variable", "variable", "variance", "variance", "variance", "variants", "variety", "variety", "various", "various", "various", "various", "vector", "vector", "vector", "vector", "vector", "visualization", "visualization", "visualization", "wave", "web", "widely", "workflows", "working", "writing", "writing", "writing", "writing", "writing", "written" ],
"Topic": [ 2, 3, 10, 5, 12, 14, 2, 13, 11, 5, 11, 12, 9, 10, 7, 9, 8, 10, 12, 10, 11, 13, 6, 10, 11, 11, 1, 5, 7, 8, 9, 11, 1, 3, 4, 13, 4, 10, 8, 12, 5, 8, 9, 14, 1, 2, 14, 9, 8, 9, 13, 8, 7, 12, 5, 8, 14, 10, 3, 12, 1, 4, 13, 7, 8, 12, 14, 6, 2, 6, 7, 9, 8, 2, 7, 13, 1, 13, 1, 7, 11, 6, 5, 6, 13, 7, 4, 11, 1, 7, 11, 14, 8, 9, 12, 9, 1, 4, 8, 2, 8, 13, 4, 12, 10, 10, 2, 11, 13, 4, 8, 3, 6, 10, 14, 8, 4, 1, 10, 12, 9, 14, 1, 1, 6, 5, 10, 3, 12, 4, 7, 13, 14, 3, 4, 6, 14, 8, 12, 3, 14, 5, 8, 4, 9, 10, 12, 5, 7, 14, 5, 6, 7, 13, 14, 6, 10, 10, 13, 13, 2, 4, 10, 14, 2, 1, 11, 6, 13, 4, 7, 10, 14, 4, 2, 3, 7, 8, 1, 2, 4, 6, 5, 10, 14, 7, 4, 1, 2, 7, 8, 13, 1, 2, 3, 5, 8, 11, 13, 1, 2, 11, 5, 9, 11, 8, 10, 11, 5, 5, 11, 8, 10, 12, 6, 8, 9, 3, 5, 2, 4, 6, 9, 1, 12, 13, 12, 4, 6, 8, 6, 6, 9, 9, 7, 13, 6, 13, 1, 13, 1, 2, 13, 4, 13, 3, 4, 10, 1, 5, 3, 2, 8, 2, 3, 12, 10, 9, 8, 3, 6, 11, 12, 10, 4, 11, 6, 3, 6, 6, 6, 7, 8, 12, 5, 7, 5, 1, 3, 12, 9, 6, 9, 11, 12, 6, 12, 1, 3, 4, 5, 12, 1, 13, 14, 2, 2, 9, 14, 8, 12, 2, 3, 11, 10, 12, 5, 12, 7, 3, 9, 12, 12, 10, 7, 5, 12, 12, 4, 7, 10, 14, 5, 6, 3, 10, 6, 13, 1, 8, 9, 13, 5, 2, 9, 13, 1, 9, 9, 9, 6, 9, 9, 12, 10, 11, 14, 7, 5, 2, 2, 12, 13, 2, 5, 10, 6, 13, 3, 14, 1, 3, 8, 10, 1, 3, 6, 11, 2, 5, 6, 7, 2, 12, 13, 1, 5, 6, 7, 11, 14, 6, 14, 3, 4, 3, 14, 1, 11, 11, 5, 6, 11, 7, 9, 14, 14, 8, 13, 3, 4, 8, 10, 13, 2, 10, 8, 3, 4, 8, 10, 14, 12, 3, 10, 10, 8, 4, 4, 14, 2, 3, 4, 4, 5, 2, 4, 9, 13, 7, 11, 4, 14, 1, 3, 10, 5, 8, 2, 7, 9, 11, 14, 1, 7, 9, 4, 5, 7, 8, 6, 1, 2, 3, 13, 2, 4, 4, 5, 7, 3, 6, 8, 9, 13, 6, 3, 4, 11, 1, 2, 3, 9, 1, 9, 1, 14, 5, 4, 14, 3, 5, 3, 9, 3, 5, 14, 8, 14, 9, 7, 8, 2, 8, 10, 12, 13, 4, 10, 6, 8, 9, 6, 2, 6, 4, 5, 9, 12, 3, 8, 13, 2, 6, 10, 1, 3, 9, 13, 6, 7, 10, 14, 1, 5, 2, 1, 3, 10, 3, 8, 14, 10, 7, 7, 9, 14, 12, 14, 7, 13, 2, 14, 1, 5, 1, 1, 3, 12, 3, 13, 8, 12, 11, 2, 14, 4, 11, 13, 14, 2, 7, 1, 6, 12, 9, 9, 6, 8, 8, 13, 1, 5, 12, 14, 7, 1, 4, 10, 6, 4, 8, 13, 5, 11, 4, 12, 2, 4, 10, 11, 4, 8, 3, 3, 6, 2, 4, 7, 8, 9, 6, 9, 10, 9, 7, 9, 11, 4, 6, 12, 1, 4, 5, 8, 4, 1, 7, 1, 6, 11, 13, 7, 14, 10, 13, 10, 8, 6, 12, 1, 2, 7, 2, 3, 6, 1, 4, 11, 13, 5, 11, 3, 7, 14, 1, 5, 7, 13, 3, 13, 4, 5, 9, 10, 4, 5, 10, 12, 4, 13, 14, 4, 7, 12, 1, 2, 11, 13, 4, 5, 13, 13, 13, 14, 9, 1, 9, 11, 12, 5, 10, 1, 5, 12, 1, 6, 11, 2, 3, 13, 11, 3, 11, 3, 2, 9, 11, 7, 10, 14, 3, 7, 11, 13, 1, 12, 1, 12, 13, 2, 9, 11, 14, 5, 4, 12, 3, 3, 4, 7, 1, 7, 8, 9, 14, 9, 7, 1, 8, 11, 8, 2, 9, 11, 13, 1, 2, 3, 10, 11, 12, 7, 1, 9, 11, 12, 11, 8, 14, 7, 8, 6, 7, 8, 6, 13, 4, 4, 12, 14, 10, 11, 9, 10, 4, 8, 5, 2, 5, 14, 9, 2, 5, 10, 13, 14, 10, 3, 8, 10, 8, 9, 10, 7, 8, 6, 9, 12, 13, 4, 6, 11, 6, 13, 2, 6, 4, 5, 7, 9, 13, 6, 5, 7, 1, 12, 7, 5, 3, 4, 9, 13, 11, 2, 6, 12, 13, 10, 3, 11, 14, 7, 12, 5, 4, 7, 8, 10, 3, 9, 5, 3, 6, 10, 14, 1, 6, 8, 1, 4, 12, 8, 13, 6, 6, 5, 8, 9, 1, 2, 4, 5, 13, 8, 4, 14, 11, 1, 7, 14, 9, 1, 3, 5, 3, 5, 3, 14, 9, 11, 1, 3, 2, 3, 8, 12, 2, 4, 11, 3, 4, 9, 10, 1, 12, 14, 3, 2, 3, 6, 7, 10, 14, 1, 2, 4, 10, 11, 1, 14, 9, 5, 6, 4, 9, 8, 6, 1, 11, 6, 7, 9, 11, 5, 14, 5, 1, 11, 4, 14, 12, 1, 2, 1, 3, 13, 10, 1, 2, 5, 8, 9, 10, 2, 5, 6, 8, 14, 2, 9, 11, 6, 3, 14, 7, 11, 3, 4, 9, 13, 14, 6 ],
"Freq": [ 0.2145038, 0.2145038, 0.4290075, 0.3051597, 0.6103194, 0.612495, 0.1824312, 0.5472937, 0.8049152, 0.5087336, 0.2543668, 0.7839841, 0.6121387, 0.8911147, 0.5046895, 0.2523448, 0.2844532, 0.1422266, 0.5689065, 0.4255709, 0.4255709, 0.2127855, 0.04608867, 0.02304434, 0.9217734, 0.8049152, 0.4174517, 0.01858814, 0.2602339, 0.4461153, 0.09294069, 0.1672932, 0.4972665, 0.1243166, 0.1243166, 0.1243166, 0.3177345, 0.6354689, 0.4213181, 0.4213181, 0.4672263, 0.2920164, 0.05840328, 0.1168066, 0.1012452, 0.2531131, 0.6327828, 0.8396823, 0.3209427, 0.3209427, 0.1604714, 0.7594095, 0.6481993, 0.1620498, 0.7641119, 0.3077199, 0.6154399, 0.8100816, 0.2443406, 0.4886811, 0.1858978, 0.1858978, 0.3717957, 0.251165, 0.5023301, 0.251165, 0.7943664, 0.8127885, 0.2190658, 0.4381316, 0.6391787, 0.2130596, 0.8043496, 0.1456093, 0.5824373, 0.1456093, 0.3080762, 0.6161524, 0.2158424, 0.2158424, 0.4316848, 0.6289832, 0.2560403, 0.5120805, 0.6009721, 0.8051837, 0.3161427, 0.6322853, 0.2159003, 0.6477009, 0.7600818, 0.7943664, 0.8043496, 0.7939668, 0.6032552, 0.7939668, 0.7960835, 0.4202892, 0.8043496, 0.0776565, 0.5435955, 0.310626, 0.9009338, 0.07507782, 0.8100816, 0.8623605, 0.7725236, 0.6147781, 0.3073891, 0.527748, 0.263874, 0.366743, 0.5501146, 0.3085552, 0.6171104, 0.6214153, 0.4202892, 0.4953419, 0.247671, 0.1238355, 0.6298455, 0.2099485, 0.9048155, 0.321073, 0.321073, 0.6254873, 0.3127437, 0.7760575, 0.7839841, 0.3162255, 0.632451, 0.6009721, 0.5649312, 0.6498028, 0.1856579, 0.09282897, 0.7943664, 0.3045948, 0.6091895, 0.5962263, 0.9077473, 0.2138425, 0.6415275, 0.118807, 0.475228, 0.237614, 0.237614, 0.2037686, 0.6113058, 0.2037686, 0.1087921, 0.1087921, 0.05439606, 0.6527527, 0.8567333, 0.3136805, 0.627361, 0.7045235, 0.2348412, 0.7814121, 0.9258622, 0.1655627, 0.6622508, 0.7943664, 0.4153466, 0.6667328, 0.2222443, 0.8127885, 0.7814121, 0.6795788, 0.1309526, 0.3928578, 0.3928578, 0.4202892, 0.1198047, 0.1198047, 0.1198047, 0.5990235, 0.2235565, 0.447113, 0.5295517, 0.2647759, 0.2892757, 0.1446379, 0.4339136, 0.8736106, 0.4202892, 0.4174517, 0.2224394, 0.1112197, 0.4448788, 0.1112197, 0.4416371, 0.1472124, 0.2944247, 0.1275342, 0.5739041, 0.2550685, 0.06376712, 0.1661536, 0.1661536, 0.4984607, 0.2037815, 0.2037815, 0.5094538, 0.1636812, 0.4910435, 0.3273623, 0.945929, 0.7437809, 0.8049152, 0.2096214, 0.2096214, 0.4192427, 0.1449704, 0.5798816, 0.2899408, 0.7760575, 0.8083011, 0.8918054, 0.785408, 0.645572, 0.2151907, 0.2132965, 0.4265931, 0.8222187, 0.9197937, 0.4202892, 0.8661992, 0.7594095, 0.8127885, 0.4250459, 0.4250459, 0.7939668, 0.5021255, 0.2510627, 0.4835417, 0.3223611, 0.1582319, 0.7911593, 0.6724948, 0.2241649, 0.7814121, 0.785408, 0.7814121, 0.1907062, 0.09535308, 0.6674716, 0.6489361, 0.8083011, 0.7260876, 0.6022471, 0.3011235, 0.8690821, 0.06685247, 0.8915567, 0.8100816, 0.7939668, 0.8043496, 0.364331, 0.1821655, 0.364331, 0.7839841, 0.7662346, 0.3161427, 0.6322853, 0.8256253, 0.3240189, 0.6480378, 0.8127885, 0.8127885, 0.8554362, 0.3045948, 0.6091895, 0.8083011, 0.8051837, 0.819158, 0.1569164, 0.7845822, 0.6032552, 0.7939668, 0.8127885, 0.5443807, 0.1814602, 0.1814602, 0.853716, 0.142286, 0.1471842, 0.1471842, 0.1471842, 0.588737, 0.7839841, 0.7778138, 0.04861336, 0.1458401, 0.4153466, 0.7725236, 0.7134925, 0.1426985, 0.8043496, 0.7839841, 0.8269599, 0.4895319, 0.244766, 0.1065139, 0.8521112, 0.2832873, 0.7082184, 0.8051837, 0.7760575, 0.6276487, 0.2092162, 0.7839841, 0.626553, 0.8051837, 0.208094, 0.624282, 0.7839841, 0.131595, 0.2631899, 0.2631899, 0.3947849, 0.8598402, 0.6289832, 0.4213478, 0.4213478, 0.3050139, 0.6100278, 0.1630419, 0.4891257, 0.3260838, 0.7814121, 0.8083011, 0.5650313, 0.1883438, 0.1883438, 0.5221654, 0.2610827, 0.8396823, 0.7939668, 0.5091687, 0.2545843, 0.2460883, 0.4921765, 0.5097914, 0.2548957, 0.7992655, 0.6221622, 0.8598402, 0.7909866, 0.5633297, 0.1877766, 0.1877766, 0.6775371, 0.1693843, 0.626553, 0.2470959, 0.4941918, 0.7760575, 0.7943664, 0.2135729, 0.2135729, 0.4271457, 0.8100816, 0.1105928, 0.1105928, 0.2211856, 0.5529639, 0.1656976, 0.3313952, 0.1656976, 0.1656976, 0.1802113, 0.3604226, 0.3604226, 0.08958659, 0.1791732, 0.08958659, 0.08958659, 0.4479329, 0.08958659, 0.2509786, 0.5019573, 0.4336219, 0.4336219, 0.4124021, 0.4124021, 0.2562578, 0.5125156, 0.8049152, 0.5102957, 0.2551478, 0.8049152, 0.5966017, 0.1193203, 0.2386407, 0.7943664, 0.2463103, 0.4926206, 0.263984, 0.131992, 0.263984, 0.263984, 0.7814121, 0.5230999,  0.26155, 0.8043496, 0.7760575, 0.5051469, 0.1683823, 0.1683823, 0.1683823, 0.9371919, 0.7520495, 0.1504099, 0.626553, 0.6214153, 0.785408, 0.6239006, 0.2495602, 0.1003122, 0.1003122, 0.7021852, 0.2578236, 0.5156472, 0.2222964, 0.4445929, 0.2222964, 0.6009721, 0.6221622, 0.8049152, 0.6690892, 0.2230297, 0.4174517, 0.8348615, 0.1391436, 0.2535265, 0.5070531, 0.7909866, 0.2602049, 0.3903074, 0.1301025, 0.1301025, 0.8017293, 0.0943211, 0.0943211, 0.1328891, 0.5315565, 0.1328891, 0.2657783, 0.7694665, 0.08646478, 0.6917183, 0.08646478, 0.08646478, 0.8285766, 0.1380961, 0.610735, 0.1526838, 0.1526838, 0.03706423, 0.9266057, 0.03706423, 0.7961257, 0.1592251, 0.8127885, 0.1456696, 0.1456696, 0.5826784, 0.1020872, 0.1020872, 0.1020872, 0.510436, 0.682653, 0.2730612, 0.7779965, 0.7943664, 0.8083011, 0.5255811, 0.2627905, 0.4901563, 0.2450781, 0.3571977, 0.3571977, 0.7003418, 0.2154898, 0.05387244, 0.8542598, 0.7943664, 0.7939668, 0.8402637, 0.1200377, 0.1604742, 0.1604742, 0.1604742, 0.3209485, 0.1604742, 0.9720117, 0.01495403, 0.6664047, 0.1110675, 0.2221349, 0.8678515, 0.6783219, 0.1695805, 0.6540844, 0.2101985, 0.420397, 0.2101985, 0.5962263, 0.4173711, 0.4173711, 0.5035107, 0.1678369, 0.3356738, 0.1799331, 0.3598662, 0.1799331, 0.1799331, 0.1307658, 0.2615316, 0.1307658, 0.3922974, 0.9705631, 0.01831251, 0.6451239, 0.6599569, 0.2199856, 0.8100816, 0.09992174, 0.09992174, 0.7993739, 0.7662346, 0.8051837, 0.2502091, 0.2502091, 0.5004183, 0.4922533, 0.2461266, 0.3039366, 0.6078733, 0.1184343,  0.82904, 0.5252282, 0.2626141, 0.6489361, 0.1598481, 0.3196961, 0.3196961, 0.7760575, 0.7814121, 0.3045948, 0.6091895, 0.8049152, 0.8207326, 0.1367888, 0.08805989, 0.3522396, 0.3522396, 0.08805989, 0.1206085, 0.8442593, 0.3752637, 0.1876318, 0.3752637, 0.9071211, 0.7471105, 0.747684, 0.186921, 0.8043496, 0.7814121, 0.3383694, 0.1691847, 0.08459234, 0.3383694, 0.8554362, 0.4460757, 0.2230378, 0.2230378, 0.8127885, 0.1865389, 0.7461557, 0.7814121, 0.3114649, 0.6229298, 0.2101717, 0.630515, 0.2183949, 0.2183949, 0.2183949, 0.4367897, 0.334134, 0.501201, 0.7760575, 0.4909782, 0.2454891, 0.2180767, 0.2180767, 0.4361534, 0.8043496, 0.7939668, 0.6289832, 0.4850433, 0.3233622, 0.9071211, 0.7374341, 0.1843585, 0.8049152, 0.2163376, 0.4326753, 0.2163376, 0.168519, 0.3370381, 0.168519, 0.3370381, 0.4202892, 0.7522799,  0.25076, 0.1863657, 0.3727315, 0.1863657, 0.1863657, 0.6221622, 0.7943664, 0.1403506, 0.7017532, 0.626553, 0.8043496, 0.4247833, 0.4247833, 0.384781, 0.1923905, 0.1923905, 0.9307349, 0.7593226, 0.2531075, 0.1396961, 0.06984803, 0.1396961, 0.5587842, 0.2536951, 0.5073902, 0.6978727, 0.1395745, 0.1395745, 0.08404268, 0.4202134, 0.3361707, 0.08404268, 0.4096224, 0.4096224, 0.04508108, 0.2254054, 0.04508108, 0.6762162, 0.06725999, 0.5380799,  0.13452,  0.20178, 0.5724602, 0.2289841, 0.114492, 0.3645643, 0.4557053, 0.09114107, 0.1891704, 0.3783409, 0.1891704, 0.1891704, 0.6540844, 0.2466796, 0.4933592, 0.6009721, 0.6193208, 0.2064403, 0.7939668, 0.1450501, 0.2901001, 0.4351502, 0.1450501, 0.6556185, 0.1639046, 0.2167971, 0.6503913, 0.7839841, 0.1116086, 0.4464345, 0.4464345, 0.9781416, 0.1772362, 0.7089448, 0.8049152, 0.7760575, 0.8049152, 0.7760575, 0.6451239, 0.5002078, 0.2501039, 0.1210383, 0.8472681, 0.7943664, 0.8148241, 0.2104214, 0.4208427, 0.4208427, 0.6773134, 0.1693284, 0.7751428, 0.09689285, 0.09689285, 0.7909866, 0.4831864, 0.3221242, 0.7475825, 0.9246577, 0.3096486, 0.6192972, 0.5962263, 0.8148241, 0.3162255, 0.632451, 0.2953139, 0.147657, 0.2953139, 0.147657, 0.147657, 0.9071211, 0.9212054, 0.5734458, 0.1911486, 0.1911486, 0.8043496, 0.1309867, 0.2619735, 0.2619735, 0.2619735, 0.1103158, 0.1103158, 0.1103158, 0.2206317, 0.1103158, 0.2206317, 0.8051837, 0.08134515, 0.08134515, 0.1626903, 0.6507612, 0.8550574, 0.8043496, 0.7943664, 0.621913, 0.3109565, 0.2541326, 0.5082651, 0.2541326, 0.3173079, 0.6346158, 0.6795788, 0.7728744, 0.1288124, 0.612495, 0.0950664, 0.8555976, 0.1463479, 0.7317397, 0.527748, 0.263874, 0.8083011, 0.333981, 0.222654, 0.445308, 0.7939668, 0.1449565, 0.1449565, 0.289913, 0.1449565, 0.289913, 0.8100816, 0.7760575, 0.8547457, 0.09497175, 0.03560024, 0.3204022, 0.6052041, 0.4274826, 0.4274826, 0.1418923, 0.2837846, 0.2837846, 0.1418923, 0.147176, 0.2943521, 0.5887042, 0.7326557, 0.1465311, 0.2582453, 0.5164907, 0.1620564, 0.1620564, 0.1620564, 0.3241127, 0.1620564, 0.8127885, 0.2140783, 0.642235, 0.2548398, 0.5096795, 0.8051837, 0.819158, 0.1807705, 0.1807705, 0.1807705, 0.3615411, 0.8049152, 0.6009353, 0.03338529, 0.2503897, 0.1001559, 0.8100816, 0.1442157, 0.5768628, 0.1442157, 0.4984482, 0.4984482, 0.6249558, 0.4066631, 0.1355544, 0.2711087, 0.2711087, 0.7537582, 0.2512527, 0.8083011, 0.7760575, 0.7694665, 0.8100816, 0.7943664, 0.693489, 0.1155815, 0.1155815, 0.7960835, 0.5232885, 0.2616443, 0.5016389, 0.2508194, 0.6289832, 0.8127885, 0.08726582, 0.08726582, 0.7853923, 0.1324226, 0.03310566, 0.03310566, 0.5627962, 0.2648453, 0.8043496, 0.6540844, 0.7943664, 0.8049152, 0.1841584, 0.1841584, 0.5524753, 0.7939668, 0.1581924, 0.6327695, 0.1581924, 0.2126108, 0.6378325, 0.7071338, 0.1767835, 0.6320347, 0.2106782, 0.1787145, 0.7148581, 0.8269599, 0.6867193, 0.1144532, 0.1144532, 0.7408123, 0.07408123, 0.07408123, 0.1651619, 0.3303238, 0.3303238, 0.1651619, 0.4427697, 0.1475899, 0.2951798, 0.7760575, 0.6341894, 0.1585473, 0.03963684, 0.03963684, 0.07927367, 0.07927367, 0.1062815, 0.212563, 0.212563, 0.212563, 0.1062815, 0.3120893, 0.6241786, 0.6121387, 0.8083011, 0.8127885, 0.4202892, 0.7939668, 0.8043496, 0.8661992, 0.6489361, 0.8049152, 0.06383579, 0.1915074, 0.1276716, 0.6383579, 0.8083011, 0.7943664, 0.6249558, 0.5735415, 0.382361, 0.2580965, 0.516193, 0.6032552, 0.5051979, 0.5051979, 0.2601312, 0.6069729, 0.08671041, 0.8100816, 0.5821227, 0.1940409, 0.1620358, 0.1620358, 0.3240716, 0.3240716, 0.07130166, 0.1426033, 0.4991116, 0.07130166, 0.1426033, 0.4432267, 0.2954844, 0.1477422, 0.8127885, 0.8148241, 0.7943664, 0.8051837, 0.8049152, 0.1810626, 0.4526565, 0.09053131, 0.09053131, 0.09053131, 0.7694665 ] 
},
"R":       30,
"lambda.step":     0.01,
"plot.opts": {
 "xlab": "PC1",
"ylab": "PC2" 
},
"topic.order": [ 11, 10, 13, 12, 2, 1, 14, 8, 7, 9, 5, 4, 3, 6 ] 
}